text_digestor/__init__.py
text_digestor/main.py
text_digestor/prompts.py
text_digestor-2025.12.22080445.dist-info/METADATA
text_digestor-2025.12.22080445.dist-info/WHEEL
text_digestor-2025.12.22080445.dist-info/top_level.txt
text_digestor-2025.12.22080445.dist-info/RECORD
