Metadata-Version: 2.4
Name: text-digestor
Version: 2025.12.22080445
Summary: Transforms raw text into clean, readable articles by removing ads, nav, sidebars, preserving core narrative with structured output.
Author-email: text-digestor <hi@eugene.plus>
License: MIT
Project-URL: Homepage, https://github.com/chigwell/text-digestor
Requires-Python: >=3.9
Requires-Dist: langchain-llm7>=0.0.0
Requires-Dist: llmatch-messages>=0.0.0
Requires-Dist: langchain-core>=0.3.0
